setup.py
bn_distributions.egg-info/PKG-INFO
bn_distributions.egg-info/SOURCES.txt
bn_distributions.egg-info/dependency_links.txt
bn_distributions.egg-info/not-zip-safe
bn_distributions.egg-info/top_level.txt
distributions/Binomialdistribution.py
distributions/Gaussiandistribution.py
distributions/Generaldistribution.py
distributions/__init__.py