Metadata-Version: 1.0
Name: bn-distributions
Version: 0.1
Summary: Gaussian, General and Binomial distributions
Home-page: UNKNOWN
Author: Gazal Gupta
Author-email: gazalgupta30@gmail.com
License: UNKNOWN
Platform: UNKNOWN
